pimsclient/__init__.py
pimsclient/auth/__init__.py
pimsclient/auth/exceptions.py
pimsclient/auth/msal.py
pimsclient/auth/ntlm.py
pimsclient/autogen/__init__.py
pimsclient/autogen/swagger_models_v0.py
pimsclient/client.py
pimsclient/core.py
pimsclient/exceptions.py
pimsclient/keyfile.py
pimsclient/logs.py
pimsclient/server.py
pimsclient/swagger.py
pimsclient-2.3.0.dist-info/LICENSE
pimsclient-2.3.0.dist-info/METADATA
pimsclient-2.3.0.dist-info/WHEEL
pimsclient-2.3.0.dist-info/RECORD
