Metadata-Version: 2.3
Name: pimsclient
Version: 2.3.0
Summary: Client for PIMS key_file management swagger web API
License: MIT
Author: sjoerdk
Author-email: sjoerd.kerkstra@radboudumc.nl
Requires-Python: >=3.9,<4.0
Classifier: License :: OSI Approved :: MIT License
Classifier: Programming Language :: Python :: 3
Classifier: Programming Language :: Python :: 3.9
Classifier: Programming Language :: Python :: 3.10
Classifier: Programming Language :: Python :: 3.11
Classifier: Programming Language :: Python :: 3.12
Classifier: Programming Language :: Python :: 3.13
Requires-Dist: msal (>=1.24.1,<2.0.0)
Requires-Dist: pydantic (>=2.11.5,<3.0.0)
Requires-Dist: requests (>=2.32.3,<3.0.0)
Requires-Dist: requests_ntlm (>=1.1.0,<2.0.0)
Project-URL: Repository, https://github.com/sjoerdk/pimsclient
